{
  "Menu": [
    {
      "title": "Warm Grain Bowls",
      "subtitle": "Warming, rejuvenating and mineral rich.",
      "items": [
        {
          "d_name": "Buddha Bowl",
          "image": "assets/item1.png",
          "description": "Avocado, beets, kale, shiitake, purple cabbage, jalapeño, tamari almonds, hemp seeds, lemon-cilantro rice & quinoa with ginger tamari sauce Contains tree nuts, soy and allium.",
          "price": "13.65",
          "category": ["V","VG","GF","DF"]
        },
        {
          "d_name": "Rainbow Harvest",
          "image": "assets/item2.png",
          "description": "Whipped sweet potato, beets, carrots, broccoli, kale, tofu & brown rice with ginger tamari sauce Contains soy and allium.",
          "price": "12.75",
          "category": ["V","VG","GF","DF","NF"]
        },
        {
          "d_name": "Southwest Sol",
          "image": "assets/item3.png",
          "description": "Avocado, sweet corn, tomato, roasted chipotle tofu with peppers & onions, purple cabbage, jalapeño, braised black beans & dirty rice topped with salsa verde Contains allium and soy",
          "price": "13.15",
          "category": ["V","VG","GF","DF","NF"]
        },
        {
          "d_name": "Green Goddess Bowl",
          "image": "assets/item4.png",
          "description": "Avocado, broccoli & kale with tofu, lemon garlic brown rice and ginger tamari sauce Contains soy and allium.",
          "price": "13.15",
          "category": ["V","VG","GF","DF","NF"]
        },
        {
          "d_name": "Innocent",
          "image": "assets/item5.png",
          "description": "Broccoli, carrots, sweet corn, roasted tamari almonds, quinoa & brown rice with ginger tamari sauce Contains tree nuts, soy and allium",
          "price": "12.50",
          "category": ["V","VG","GF","DF"]
        },
        {
          "d_name": "Emperor Bowl",
          "image": "assets/item6.png",
          "description": "Tofu, corn, carrots, sun-dried tomatoes, kale & cheddar rice with red miso sauce Contains dairy, soy, sesame and allium",
          "price": "12.50",
          "category": ["V","GF","NF"]
        },
        {
          "d_name": "Lover",
          "image": "assets/item7.png",
          "description": "Shiitake, beets, carrots, broccoli & kale with ginger tamari sauce Contains soy and allium.",
          "price": "12.50",
          "category": ["V","VG","GF","DF","NF"]
        },
        {
          "d_name": "Adventurer Bowl",
          "image": "assets/item8.png",
          "description": "Red beets, broccoli, kale, fresh corn, tofu, tamari almonds with quinoa & cheddar rice, sesame & tamari ginger sauces Contains tree nuts, dairy, sesame, soy and allium.",
          "price": "12.75",
          "category": ["V","GF"]
        },
        {
          "d_name": "Swami Bowl",
          "image": "assets/item9.png",
          "description": "Broccoli, carrots, onions, kale, roasted almonds & raisins with curry brown rice and sweet red miso sauce Contains tree nuts, soy, sesame and allium.",
          "price": "12.50",
          "category": ["V","VG","GF","DF"]
        }
      ]
    },
    {
      "title": "Salads",
      "subtitle": "Energizing, complex and satisfying.",
      "items": [
        {
          "d_name": "Elote Avocado",
          "image": "assets/item10.png",
          "description": "Avocado, sweet corn, roasted chipotle tofu with peppers & onions, tomato, mixed baby lettuces, romaine hearts, shaved cabbages, pickled onions, jalapeño, black beans, chili-lime crema & salsa verde Contains dairy, allium and soy",
          "price": "12.95",
          "category": ["V","VG","NF"]
        },
        {
          "d_name": "Avocado Greens",
          "image": "assets/item11.png",
          "description": "Everything-encrusted avocado, cucumber, sweet corn, pickled onions, kalamata olives, crispy chickpeas, feta, mixed baby lettuces, romaine hearts and tomato vinaigrette Contains dairy, soy, sesame and allium",
          "price": "13.25",
          "category": ["V","GF","NF"]
        },
        {
          "d_name": "Greek Tahin",
          "image": "assets/item12.png",
          "description": "Cucumber, tomato, feta, kalamata olives, hummus & tahini, shredded carrots, pickled onion, crispy chickpeas with mixed baby lettuces, romaine hearts and greek vinaigrette Contains sesame, dairy, allium and soy",
          "price": "12.95",
          "category": ["V","GF","NF"]
        },
        {
          "d_name": "Tuscan Kale",
          "image": "assets/item13.png",
          "description": "Tuscan kale, green apples, shaved fennel, roasted cashews, dried cranberries, cashew parmesan & basil green goddess dressing Contains tree nuts and allium",
          "price": "12.50",
          "category": ["V","VG","GF","DF","S"]
        },
        {
          "d_name": "Chilled Thai Noodles",
          "image": "assets/item14.jpeg",
          "description": "Rice noodles, sugar snap peas, red bell pepper, cucumber, celery, carrot, cabbages, cilantro, mint and peanut crumble with peanut lime sauce & sweet chili coconut sauce (contains cashews) Contains peanuts, tree nuts, sesame, soy and allium",
          "price": "12.95",
          "category": ["V","VG","GF","DF"]
        }

      ]
    },
    {
      "title": "Wraps",
      "subtitle": "Flavorful, filling, and nutrient dense.",
      "items": [
        {
          "d_name": "Mediterranean Chickpea",
          "image": "assets/item15.jpeg",
          "description": "Hummus & crispy chickpeas with feta, cucumber, tomato, shredded carrots, pickled onions, kalamata olives, mixed lettuces and tahini dressing in a whole wheat tortilla Contains gluten, dairy, sesame, allium and soy. Cannot be made gluten free.",
          "price": "12.95",
          "category": ["V","NF"]
        },
        {
          "d_name": "Rainbow Harvest",
          "image": "assets/item16.png",
          "description": "Whipped sweet potato, beets, carrots, broccoli, kale, tofu & brown rice with ginger tamari sauce Contains soy and allium.",
          "price": "12.75",
          "category": ["V","VG","GF","DF","NF"]
        },
        {
          "d_name": "Rainbow Nori Wrap",
          "image": "assets/item17.png",
          "description": "Gluten-free nori rolled with avocado, shiitake & enoki mushrooms, carrots, cucumber, purple cabbage, pickled onions, cilantro & mint and brown rice with ginger carrot miso vinaigrette and tamari dipping sauce Contains allium, soy and sesame",
          "price": "12.95",
          "category": ["V","VG","GF","DF","NF"]
        },
        {
          "d_name": "Teriyaki Shiitake Wrap",
          "image": "assets/item18.png",
          "description": "Teriyaki glazed tofu, roasted shiitake, broccoli, charred onion, sweet potato, scallions, black sesame brown rice in a whole wheat tortilla Allergens: gluten, allium, sesame, soy",
          "price": "12.95",
          "category": ["V","VG","DF","NF"]
        },
        {
          "d_name": "Romantic",
          "image": "assets/item19.png",
          "description": "Melted cheddar, avocado, broccoli, garlic, Braggs & nutritional yeast pressed in a whole wheat tortilla Contains dairy, gluten, soy and allium. Item cannot be made gluten-free.",
          "price": "12.50",
          "category": ["V","NF"]
        },
        {
          "d_name": "Hot & Healthy Bachelor",
          "image": "assets/item20.png",
          "description": "Melted cheddar, steamed egg, broccoli, kale, Braggs & nutritional yeast pressed in a whole wheat tortilla Contains eggs, dairy, gluten and soy. Item cannot be made gluten-free.",
          "price": "12.25",
          "category": ["V","NF"]
        }
      ]
    },
    {
      "title": "Noodles",
      "subtitle": "Nourishing, substantial and healing.",
      "items": [
        {
          "d_name": "Blonde Miso",
          "image": "assets/item21.png",
          "description": "Miso broth with broccoli, shiitake, purple cabbage, kimchi, scallion, enoki mushrooms, hard boiled egg & udon noodles Contains eggs, gluten, soy and allium.Make it gluten-free by removing the noodles and adding rice or quinoa.",
          "price": "13.50",
          "category": ["V","DF","NF"]
        },
        {
          "d_name": "Fool II",
          "image": "assets/item22.png",
          "description": "Tofu, kale, shiitake, onion, shredded carrots, lemon, scallion & udon noodles with sesame ginger sauce Contains gluten, soy, sesame and allium.Make it gluten-free by removing the noodles and adding rice or quinoa.",
          "price": "12.75",
          "category": ["V","VG","DF","NF"]
        }
      ]
    },
    {
      "title": "Soups",
      "subtitle": "Seasonal soups, prepared daily.",
      "items": [
        {
          "d_name": "Miso Soup",
          "image": "assets/item23.png",
          "description": "Tofu, scallion & shiitake Contains soy, sesame and allium.",
          "price": "6.95",
          "category": ["GF","VG","DF","NF"]
        },
        {
          "d_name": "Butternut Bisque",
          "image": "assets/item24.jpeg",
          "description": "Roasted butternut squash, green apple, cinnamon & nutmeg topped with scallions Contains allium.",
          "price": "7.15",
          "category": ["V","VG","GF","DF","NF","S"]
        },
        {
          "d_name": "Smoky Three-Bean Chili",
          "image": "assets/item25.jpeg",
          "description": "Kidney & black beans, chickpeas, sweet potato, topped with scallion, pickled onions & sweet corn.Contains soy and allium.",
          "price": "7.25",
          "category": ["V","VG","GF","DF","NF"]
        }
      ]
    },
    {
      "title": "Small Bites",
      "subtitle": "The perfect pick-me-up",
      "items": [
        {
          "d_name": "Avocado Toast",
          "image": "assets/item26.png",
          "description": "Avocado with lemon, chili, sea salt, alfalfa sprouts & radish on a sprouted seed & grain muffin Contains soy and gluten. Cannot be made gluten free.",
          "price": "8.75",
          "category": ["V","VG","DF","NF"]
        },
        {
          "d_name": "Hummus & Pita Plate",
          "image": "assets/item27.png",
          "description": "Hummus with lemon tahini, cucumber, kalamata olives, fresh herbs, crispy chickpeas and toasted whole wheat pita Contains gluten, sesame, allium and soy.Make it gluten free by removing the pita.",
          "price": "7.75",
          "category": ["V","VG","DF","NF"]
        },
        {
          "d_name": "Steamed Edamame",
          "image": "assets/item28.png",
          "description": "Steamed with Sea Salt Contains soy",
          "price": "6.50",
          "category": ["V","VG","GF","DF","NF"]
        },{
          "d_name": "Quesadilla",
          "image": "assets/item29.png",
          "description": "Melted cheddar & nutritional yeast pressed in a whole wheat tortilla Contains gluten, soy and dairy. Item cannot be made gluten-free.",
          "price": "7.50",
          "category": ["V","NF"]
        }
      ]
    },
    {
      "title": "Acai Bowls",
      "subtitle": "luscious, dairy free and complete",
      "items": [
        {
          "d_name": "Super Berry Acai",
          "image": "assets/item30.png",
          "description": "Açaí with blueberry, strawberry, cacao nibs, coconut & almond granola Contains tree nuts.",
          "price": "12.50",
          "category": ["V","VG","GF","DF"]
        },
        {
          "d_name": "PB & J Acai Bowl",
          "image": "assets/item31.png",
          "description": "Açaí with strawberry, peanut butter, peanut crumble, hemp & almond granola Contains peanuts and tree nuts.",
          "price": "12.50",
          "category": ["V","VG","GF","DF"]
        },
        {
          "d_name": "Peanut Butter Cup",
          "image": "assets/item32.png",
          "description": "Acai, superfood fudge, banana, coconut flakes, peanut butter, almond granola",
          "price": "12.50",
          "category": ["V","VG","GF","DF"]
        }
      ]
    },
    {
      "title": "Smoothies",
      "subtitle": "Dairy free, color and flavor rich.",
      "items": [
        {
          "d_name": "Strawberries & Cream",
          "image": "assets/item33.png",
          "description": "Strawberries, housemade strawberry syrup, coconut gelato topped with vanilla cold foam",
          "price": "9.25",
          "category": ["V","VG","GF","DF","NF"]
        },
        {
          "d_name": "Super Greens",
          "image": "assets/item34.jpeg",
          "description": "Mango, pineapple, orange, kale, avocado, banana, ginger, spirulina, coconut milk",
          "price": "9.25",
          "category": ["V","VG","GF","DF","NF"]
        },
        {
          "d_name": "Elvis Alive",
          "image": "assets/item35.png",
          "description": "Peanut butter, banana, raw cacao, coconut gelato, coconut milk Contains peanuts.",
          "price": "9.25",
          "category": ["V","VG","GF","DF"]
        },
        {
          "d_name": "Blue Raspberry Acai",
          "image": "assets/item36.png",
          "description": "Açaí, blueberry, raspberry, lemon, coconut milk",
          "price": "9.25",
          "category": ["V","VG","GF","DF","NF"]
        },
        {
          "d_name": "Mango Slush",
          "image": "assets/item37.png",
          "description": "Mango, pineapple, lemon, watermelon juice",
          "price": "8.95",
          "category": ["V","VG","GF","DF","NF"]
        },
        {
          "d_name": "Love Child",
          "image": "assets/item38.png",
          "description": "Strawberry, blueberry, banana, chia, dates, coconut milk",
          "price": "8.95",
          "category": ["V","VG","GF","DF","NF"]
        },
        {
          "d_name": "Frozen Mochaccino",
          "image": "assets/item39.png",
          "description": "Cold brew, coconut gelato, vanilla, superfood fudge & maca",
          "price": "9.25",
          "category": ["V","VG","GF","DF","NF"]
        }
      ]
    },
    {
      "title": "Fresh Pressed Juices",
      "subtitle": "Fresh-pressed tonics and elixirs.",
      "items": [
        {
          "d_name": "Spicy Green Tonic",
          "image": "assets/item40.jpeg",
          "description": "Pineapple, jalapeño, mint, cilantro, green apple",
          "price": "7.95",
          "category": ["V","VG","GF","DF","NF"]
        },
        {
          "d_name": "Go Green",
          "image": "assets/item41.jpeg",
          "description": "Cucumber, celery, lemon, green apple, aloe",
          "price": "7.95",
          "category": ["V","VG","GF","DF","NF"]
        },
        {
          "d_name": "Beta Carrotene",
          "image": "assets/item42.jpeg",
          "description": "Apples, Carrots, Ginger",
          "price": "7.95",
          "category": ["V","VG","GF","DF"]
        },
        {
          "d_name": "Heart Beet",
          "image": "assets/item43.png",
          "description": "Beet, carrot, green apple, lemon, ginger",
          "price": "7.95",
          "category": ["V","VG","GF","DF","NF"]
        },
        {
          "d_name": "Morning Moxie",
          "image": "assets/item44.jpeg",
          "description": "Carrot, apple, ginger, lemon, honey, cinnamon, apple cider vinegar",
          "price": "7.95",
          "category": ["V","VG","GF","DF","NF"]
        }

      ]
    },
    {
      "title": "Lattes",
      "subtitle": "Enjoyed Hot or Iced",
      "items": [
        {
          "d_name": "Iced Ocean Blue",
          "image": "assets/item45.png",
          "description": "Blue-green algae, maca, vanilla, maple, sea salt, coconut milk",
          "price": "5.35",
          "category": ["V","VG","GF","DF","NF"]
        },
        {
          "d_name": "Iced Golden Milk",
          "image": "assets/item46.png",
          "description": "Turmeric, ginger, cinnamon, cayenne, black pepper, maple, coconut milk",
          "price": "5.35",
          "category": ["V","VG","GF","DF","NF"]
        },
        {
          "d_name": "Iced Mexican Chocolate",
          "image": "assets/item47.png",
          "description": "Cacao, cinnamon, cayenne, maple, coconut milk",
          "price": "5.35",
          "category": ["V","VG","GF","DF"]
        },
        {
          "d_name": "Hot Golden Milk",
          "image": "assets/item48.jpeg",
          "description": "Turmeric, ginger, cinnamon, cayenne, black pepper, maple, coconut milk",
          "price": "5.35",
          "category": ["V","VG","GF","DF","NF"]
        },
        {
          "d_name": "Hot Mexican Chocolate",
          "image": "assets/item49.png",
          "description": "Cacao, cinnamon, cayenne, maple, coconut milk",
          "price": "5.35",
          "category": ["V","VG","GF","DF","NF"]
        },
        {
          "d_name": "Hot Ocean Blue",
          "image": "assets/item50.png",
          "description": "Blue-green algae, maca, vanilla, maple, sea salt, coconut milk",
          "price": "5.35",
          "category": ["V","VG","GF","DF","NF"]
        },
        {
          "d_name": "Iced Matcha Latte",
          "image": "assets/item51.png",
          "description": "Premium grade matcha, oat milk",
          "price": "5.65",
          "category": ["V","VG","GF","DF","NF"]
        },
        {
          "d_name": "Hot Matcha Latte",
          "image": "assets/item52.png",
          "description": "Premium grade matcha, oat milk",
          "price": "5.65",
          "category": ["V","VG","GF","DF","NF"]
        },
        {
          "d_name": "Hot Butternut Spice Latte",
          "image": "assets/item53.jpeg",
          "description": "Roasted butternut squash, cinnamon, nutmeg, vanilla, maple & coconut milk",
          "price": "5.65",
          "category": ["V","VG","GF","DF","NF"]
        },
        {
          "d_name": "Hot Chai Latte",
          "image": "assets/item54.jpeg",
          "description": "Masala chai tea, oat milk",
          "price": "5.65",
          "category": ["V","VG","GF","DF","NF"]
        },
        {
          "d_name": "Iced Chai Latte",
          "image": "assets/item55.jpeg",
          "description": "Masala chai tea, oat milk",
          "price": "5.65",
          "category": ["V","VG","GF","DF","NF"]
        },
        {
          "d_name": "Iced Butternut Spice Latte",
          "image": "assets/item56.jpeg",
          "description": "Roasted butternut squash, cinnamon, nutmeg, vanilla, maple & coconut milk",
          "price": "5.65",
          "category": ["V","VG","GF","DF","NF"]
        }
      ]
    },
    {
      "title": "Hand Crafted",
      "subtitle": "Shaken or stirred, sparkling or brewed.",
      "items": [
        {
          "d_name": "Strawberry Lemonade",
          "image": "assets/item57.png",
          "description": "Strawberry, lemon, maple",
          "price": "4.95",
          "category": ["V","VG","GF","DF","NF"]
        },
        {
          "d_name": "Ginger Crush",
          "image": "assets/item58.png",
          "description": "Ginger, lemon, maple, crushed ice",
          "price": "5.75",
          "category": ["V","VG","GF","DF","NF"]
        },
        {
          "d_name": "Raspberry Iced Tea",
          "image": "assets/item59.png",
          "description": "Iced black tea with raspberry, honey, lemon & ginger",
          "price": "3.95",
          "category": ["V","GF","DF","NF","SF"]
        },
        {
          "d_name": "Honey Lemon Iced Tea",
          "image": "assets/item60.png",
          "description": "Iced black tea, lemon, honey & ginger",
          "price": "3.95",
          "category": ["V","GF","DF","NF","SF"]
        },
        {
          "d_name": "Classic Iced Tea",
          "image": "assets/item61.png",
          "description": "Iced black tea & fresh lemon",
          "price": "3.50",
          "category": ["V","VG","GF","DF","NF","SF"]
        },
        {
          "d_name": "Watermelon Cooler",
          "image": "assets/item62.png",
          "description": "Watermelon, cardamom, fresh mint",
          "price": "6.95",
          "category": ["V","VG","GF","DF","NF"]
        },
        {
          "d_name": "Winter Herbal Tea",
          "image": "assets/item63.png",
          "description": "Rosemary, lemon, turmeric, cinnamon & maple",
          "price": "3.95",
          "category": ["V","VG","GF","DF","NF"]
        }
      ]
    },
    {
      "title": "Coffee and Tea",
      "subtitle": "lovingly supported by Intelligentsia",
      "items": [
        {
          "d_name": "Classic Iced Tea",
          "image": "assets/item64.png",
          "description": "Iced black tea & fresh lemon",
          "price": "3.50",
          "category": ["V","VG","GF","DF","NF"]
        },
        {
          "d_name": "Fresh Mint Tea",
          "image": "assets/item65.png",
          "description": "Ginger, lemon & fresh mint",
          "price": "3.95",
          "category": ["V","VG","GF","DF","NF"]
        },
        {
          "d_name": "Fresh Lemon Honey Ginger Tea",
          "image": "assets/item66.jpeg",
          "description": "Hot fresh lemon and ginger juices, honey",
          "price": "3.95",
          "category": ["V","GF","DF","NF"]
        },
        {
          "d_name": "Honey Lemon Iced Tea",
          "image": "assets/item67.png",
          "description": "Iced black tea, lemon, honey & ginger",
          "price": "3.95",
          "category": ["V","GF","DF","NF"]
        },
        {
          "d_name": "Raspberry Iced Tea",
          "image": "assets/item68.png",
          "description": "Iced black tea with raspberry, honey, lemon & ginger",
          "price": "3.95",
          "category": ["V","GF","DF","NF"]
        },
        {
          "d_name": "Winter Herbal Tea",
          "image": "assets/item69.png",
          "description": "Rosemary, lemon, turmeric, cinnamon & maple",
          "price": "3.95",
          "category": ["V","VG","GF","DF","NF"]
        },
        {
          "d_name": "Cold Brew Coffee",
          "image": "assets/item70.png",
          "description": "Smooth & strong",
          "price": "4.95",
          "category": ["V","VG","GF","DF","NF"]
        },
        {
          "d_name": "Vanilla Honey Oat Cold Brew",
          "image": "assets/item71.png",
          "description": "Cold brew, honey, vanilla & oat milk",
          "price": "5.25",
          "category": ["V","GF","DF","NF"]
        },
        {
          "d_name": "Maple Vanilla Cloud Cold Brew",
          "image": "assets/item72.png",
          "description": "Cold brew topped with maple vanilla cold foam",
          "price": "6.50",
          "category": ["V","VG","GF","DF","NF"]
        }
      ]
    },
    {
      "title": "Bottled Beverages",
      "subtitle": "Locally sourced partners.",
      "items": [
        {
          "d_name": "Box Water",
          "image": "assets/item73.png",
          "description": "",
          "price": "2.25",
          "category": []
        }

      ]
    },
    {
      "title": "Shots",
      "subtitle": "Wellness boosts for anytime of day.",
      "items": [
        {
          "d_name": "Turmeric 1oz",
          "image": "assets/item74.png",
          "description": "",
          "price": "2.50",
          "category": ["V","VG","GF","DF","NF"]
        },
        {
          "d_name": "Ginger 1oz",
          "image": "assets/item75.png",
          "description": "",
          "price": "2.50",
          "category": ["V","VG","GF","DF","NF"]
        }
      ]
    },
    {
      "title": "Desserts",
      "subtitle": "Hand-made vegan treats",
      "items": [
        {
          "d_name": "Maple Pecan Overnight Oats",
          "image": "assets/item76.jpeg",
          "description": "Gluten-free oats with candied pecans (contains butter), maple, dried cranberries, chia, flax, hemp seeds, coconut flakes, cacao nibs & bee pollen Contains tree nuts, dairy and sesame.",
          "price": "6.95",
          "category": ["V"]
        }
      ]
    },
    {
      "title": "Housemade Signature Sauce",
      "subtitle": "House-made accompaniments to any meal.",
      "items": [
        {
          "d_name": "Ginger Tamari Gluten Free 8oz",
          "image": "assets/item77.png",
          "description": "Fresh ginger, tamari, garlic, lemon, olive oil & spices",
          "price": "12.00",
          "category": ["V"]
        }
      ]
    },
    {
      "title": "Kids Menu",
      "subtitle": "",
      "items": [
        {
          "d_name": "Quesadilla",
          "image": "assets/item78.png",
          "description": "Melted cheddar & nutritional yeast pressed in a whole wheat tortilla Contains gluten, soy and dairy. Item cannot be made gluten-free.",
          "price": "7.50",
          "category": ["V","NF"]
        }
      ]
    }
  ]
}